{
  "project_info": {
    "project_number": "96924074074",
    "firebase_url": "https://quizable-40190.firebaseio.com",
    "project_id": "quizable-40190",
    "storage_bucket": "quizable-40190.appspot.com"
  },
  "client": [
    {
      "client_info": {
        "mobilesdk_app_id": "1:96924074074:android:832f752d0c67987a961863",
        "android_client_info": {
          "package_name": "com.innoventixsolutions.quizable"
        }
      },
      "oauth_client": [
        {
          "client_id": "96924074074-60c98tvd5mm603qc0sc6ok7hj32jo2bf.apps.googleusercontent.com",
          "client_type": 3
        }
      ],
      "api_key": [
        {
          "current_key": "AIzaSyDKG92-_KQ96pGbUD6coqt5f_EmD-bxFnA"
        }
      ],
      "services": {
        "appinvite_service": {
          "other_platform_oauth_client": [
            {
              "client_id": "96924074074-60c98tvd5mm603qc0sc6ok7hj32jo2bf.apps.googleusercontent.com",
              "client_type": 3
            },
            {
              "client_id": "96924074074-q7dnvoeknd1l39g2fi0k9nt8566vv4mi.apps.googleusercontent.com",
              "client_type": 2,
              "ios_info": {
                "bundle_id": "com.innoventixsolution.quizable"
              }
            }
          ]
        }
      }
    }
  ],
  "configuration_version": "1"
}